mt/cmd/__init__.py
mt/cmd/version.py
mtcmd-0.2.1.data/scripts/git_binst.sh
mtcmd-0.2.1.data/scripts/git_commit_sync.sh
mtcmd-0.2.1.data/scripts/git_emac.sh
mtcmd-0.2.1.data/scripts/mt_update.py
mtcmd-0.2.1.dist-info/licenses/LICENSE
mtcmd-0.2.1.dist-info/METADATA
mtcmd-0.2.1.dist-info/WHEEL
mtcmd-0.2.1.dist-info/top_level.txt
mtcmd-0.2.1.dist-info/RECORD
